listful/__init__.py
listful/_internal/__init__.py
listful/_internal/testing_utils.py
listful/exceptions.py
listful/index.py
listful/listful.py
listful/types.py
listful/utils.py
listful-0.3.0.dist-info/LICENSE
listful-0.3.0.dist-info/WHEEL
listful-0.3.0.dist-info/METADATA
listful-0.3.0.dist-info/RECORD
