Metadata-Version: 2.1
Name: listful
Version: 0.3.0
Summary: efficient filtering of lists of objects
Home-page: https://pypi.org/project/listful
License: MIT
Author: David S
Author-email: d1618033@gmail.com
Requires-Python: >=3.7,<4.0
Classifier: License :: OSI Approved :: MIT License
Classifier: Programming Language :: Python :: 3
Classifier: Programming Language :: Python :: 3.7
Classifier: Programming Language :: Python :: 3.8
Classifier: Programming Language :: Python :: 3.9
Project-URL: Repository, https://github.com/d1618033/listful
